secrets_cache/__init__.py
secrets_cache/__main__.py
secrets_cache/_aws.py
secrets_cache/_cache.py
secrets_cache/_constants.py
secrets_cache/cli.py
secrets_cache-0.3.2.dist-info/licenses/LICENSE
secrets_cache-0.3.2.dist-info/METADATA
secrets_cache-0.3.2.dist-info/WHEEL
secrets_cache-0.3.2.dist-info/entry_points.txt
secrets_cache-0.3.2.dist-info/top_level.txt
secrets_cache-0.3.2.dist-info/RECORD
