Metadata-Version: 2.4
Name: secrets-cache
Version: 0.3.2
Summary: In-memory caching for AWS Secrets Manager / SSM in Lambda, with optional file-based cache for local use.
Author-email: Ritvik Nag <me@ritviknag.com>
Maintainer-email: Ritvik Nag <me@ritviknag.com>
License: MIT
Project-URL: Source, https://github.com/rnag/py-secrets-cache
Project-URL: Homepage, https://secrets-cache.ritviknag.com
Project-URL: Bug Tracker, https://github.com/rnag/py-secrets-cache/issues
Project-URL: Changelog, https://github.com/rnag/py-secrets-cache/blob/main/HISTORY.md
Keywords: aws,secrets,ssm,cache,lambda,secrets-manager,parameter-store
Classifier: Development Status :: 4 - Beta
Classifier: Intended Audience :: Developers
Classifier: Natural Language :: English
Classifier: License :: OSI Approved :: MIT License
Classifier: Programming Language :: Python
Classifier: Programming Language :: Python :: 3
Classifier: Programming Language :: Python :: 3.10
Classifier: Programming Language :: Python :: 3.11
Classifier: Programming Language :: Python :: 3.12
Classifier: Programming Language :: Python :: 3.13
Classifier: Programming Language :: Python :: 3.14
Classifier: Programming Language :: Python :: Implementation :: CPython
Classifier: Topic :: Software Development
Requires-Python: >=3.10
License-File: LICENSE
Provides-Extra: cli
Requires-Dist: typer; extra == "cli"
Provides-Extra: local
Requires-Dist: boto3>=1.26; extra == "local"
Requires-Dist: tomli-w>=1.0; extra == "local"
Requires-Dist: tomli>=2.0; python_version < "3.11" and extra == "local"
Provides-Extra: docs
Requires-Dist: mkdocs; extra == "docs"
Requires-Dist: mkdocs-material; extra == "docs"
Requires-Dist: mkdocs-github-admonitions-plugin; extra == "docs"
Requires-Dist: mkdocs-markdownextradata-plugin; extra == "docs"
Requires-Dist: mkdocs-macros-plugin; extra == "docs"
Requires-Dist: mkdocs-include-markdown-plugin; extra == "docs"
Provides-Extra: lambda
Provides-Extra: dev
Requires-Dist: bump2version; extra == "dev"
Provides-Extra: test
Requires-Dist: coverage; extra == "test"
Requires-Dist: pytest; extra == "test"
Requires-Dist: ruff; extra == "test"
Requires-Dist: ty; extra == "test"
Requires-Dist: ipdb; extra == "test"
Dynamic: license-file
